collectd_cuda/__init__.py
collectd_cuda/collectd_plugin.py
collectd_cuda-0.0.3.dist-info/DESCRIPTION.rst
collectd_cuda-0.0.3.dist-info/METADATA
collectd_cuda-0.0.3.dist-info/RECORD
collectd_cuda-0.0.3.dist-info/WHEEL
collectd_cuda-0.0.3.dist-info/metadata.json
collectd_cuda-0.0.3.dist-info/pbr.json
collectd_cuda-0.0.3.dist-info/top_level.txt
