Metadata-Version: 2.0
Name: collectd-cuda
Version: 0.0.3
Summary: CollectD plugin for Nvidia CUDA statistics
Home-page: https://github.com/Yuav/collectd-cuda
Author: Jon Skarpeteig
Author-email: jon.skarpeteig@gmail.com
License: UNKNOWN
Keywords: collectd-cuda
Platform: UNKNOWN
Requires-Dist: collectd
